MANIFEST.in
README.rst
setup.py
floraconcierge/__init__.py
floraconcierge/cache.py
floraconcierge/chat.py
floraconcierge/errors.py
floraconcierge/middleware.py
floraconcierge/panels.py
floraconcierge/services.py
floraconcierge/utils.py
floraconcierge/apiauth/__init__.py
floraconcierge/apiauth/admin.py
floraconcierge/apiauth/backends.py
floraconcierge/apiauth/models.py
floraconcierge/apiauth/migrations/0001_initial.py
floraconcierge/apiauth/migrations/0002_auto_20150524_0241.py
floraconcierge/apiauth/migrations/__init__.py
floraconcierge/client/__init__.py
floraconcierge/client/handlers.py
floraconcierge/client/types.py
floraconcierge/client/utils.py
floraconcierge/mapping/__init__.py
floraconcierge/mapping/api/__init__.py
floraconcierge/mapping/api/result/__init__.py
floraconcierge/mapping/api/result/order/__init__.py
floraconcierge/mapping/api/validation/__init__.py
floraconcierge/mapping/mixins/__init__.py
floraconcierge/mapping/mixins/model/__init__.py
floraconcierge/mapping/mixins/model/shop/__init__.py
floraconcierge/mapping/model/__init__.py
floraconcierge/mapping/model/geo/__init__.py
floraconcierge/mapping/model/inflect/__init__.py
floraconcierge/mapping/model/shop/__init__.py
floraconcierge/mapping/model/shop/order/__init__.py
floraconcierge/mapping/model/shop/order/reasons/__init__.py
floraconcierge/mapping/model/shop/product/__init__.py
floraconcierge/mapping/model/shop/promo/__init__.py
floraconcierge/mapping/model/user/__init__.py
floraconcierge/mapping/model/user/social/__init__.py
floraconcierge/shortcuts/__init__.py
floraconcierge/shortcuts/auth.py
floraconcierge/shortcuts/discount.py
floraconcierge/shortcuts/geo.py
floraconcierge/shortcuts/img.py
floraconcierge/shortcuts/invoices.py
floraconcierge/shortcuts/partner.py
floraconcierge/shortcuts/phone.py
floraconcierge/shortcuts/shop.py
floraconcierge/shortcuts/system.py
floraconcierge/shortcuts/users.py
floraconcierge/shortcuts/validation.py
floraconcierge_client.egg-info/PKG-INFO
floraconcierge_client.egg-info/SOURCES.txt
floraconcierge_client.egg-info/dependency_links.txt
floraconcierge_client.egg-info/requires.txt
floraconcierge_client.egg-info/top_level.txt