Metadata-Version: 1.1
Name: floraconcierge-client
Version: 0.7.51
Summary: FloraExpress API python client library. www.floraexpress.ru
Home-page: http://www.floraexpress.ru/
Author: Alexandr Shurigin
Author-email: alexandr.shurigin@gmail.com
License: BSD
Keywords: floraconcierge floraexpress ecommerce api adapter client
Platform: UNKNOWN
Classifier: Development Status :: 3 - Alpha
Classifier: Intended Audience :: Customer Service
Classifier: Intended Audience :: Information Technology
Classifier: Intended Audience :: Legal Industry
Classifier: License :: OSI Approved :: BSD License
Classifier: Natural Language :: English
Classifier: Natural Language :: Russian
Classifier: Operating System :: OS Independent
Classifier: Programming Language :: Python
Classifier: Programming Language :: PHP
Classifier: Topic :: Database :: Front-Ends
Classifier: Topic :: Software Development :: Libraries
Classifier: Topic :: Software Development :: Embedded Systems
